{
  "clock": {},
  "includes": [],
  "objects": [
    {
      "name": "inverter_dyn",
      "attributes": {
        "name": "trip_shad_inv1",
        "parent": "load_42",
        "flags": "DELTAMODE",
        "rated_power": "600 kW",
        "control_mode": "GFL_CURRENT_SOURCE",
        "grid_following_mode": "POSITIVE_SEQUENCE",
        "frequency_watt": "false",
        "volt_var": "false",
        "Pref": "450000",
        "Qref": "0.0",
        "kpPLL": "50",
        "kiPLL": "900",
        "Tpf": "0.50",
        "Tff": "0.01",
        "Rp": "0.05",
        "Rq": "0.05",
        "Tqf": "0.2",
        "Tvf": "0.05"
      },
      "children": []
    },
    {
      "name": "inverter_dyn",
      "attributes": {
        "name": "trip_shad_inv2",
        "parent": "node_101",
        "flags": "DELTAMODE",
        "rated_power": "180 kW",
        "control_mode": "GFL_CURRENT_SOURCE",
        "grid_following_mode": "POSITIVE_SEQUENCE",
        "frequency_watt": "false",
        "volt_var": "false",
        "Pref": "126000",
        "Qref": "0.0",
        "kpPLL": "50",
        "kiPLL": "900",
        "Tpf": "0.50",
        "Tff": "0.01",
        "Rp": "0.05",
        "Rq": "0.05",
        "Tqf": "0.2",
        "Tvf": "0.05"
      },
      "children": []
    },
    {
      "name": "inverter_dyn",
      "attributes": {
        "name": "trip_shad_inv3",
        "parent": "load_761",
        "rated_power": "120 kW",
        "flags": "DELTAMODE",
        "control_mode": "GFL_CURRENT_SOURCE",
        "grid_following_mode": "POSITIVE_SEQUENCE",
        "frequency_watt": "false",
        "volt_var": "false",
        "Pref": "84000",
        "Qref": "0.0",
        "kpPLL": "50",
        "kiPLL": "900",
        "Tpf": "0.50",
        "Tff": "0.01",
        "Rp": "0.05",
        "Rq": "0.05",
        "Tqf": "0.2",
        "Tvf": "0.05"
      },
      "children": []
    },
    {
      "name": "inverter_dyn",
      "attributes": {
        "name": "trip_shad_inv4",
        "parent": "load_51",
        "flags": "DELTAMODE",
        "rated_power": "400 kW",
        "control_mode": "GRID_FORMING",
        "Pref": "210000",
        "Qref": "0.0",
        "Rfilter": "0.0025",
        "Xfilter": "0.05",
        "mp": "3.77",
        "kppmax": "10",
        "kipmax": "20",
        "Pmax": "1.2",
        "Pmin": "0",
        "mq": "0.05"
      },
      "children": []
    },
    {
      "name": "inverter_dyn",
      "attributes": {
        "name": "trip_shad_inv5",
        "parent": "node_105",
        "flags": "DELTAMODE",
        "rated_power": "600 kW",
        "control_mode": "GRID_FORMING",
        "Pref": "300000",
        "Qref": "0.0",
        "Rfilter": "0.0025",
        "Xfilter": "0.05",
        "mp": "3.77",
        "kppmax": "10",
        "kipmax": "20",
        "Pmax": "1.2",
        "Pmin": "0",
        "mq": "0.05"
      },
      "children": []
    },
    {
      "name": "inverter_dyn",
      "attributes": {
        "name": "trip_shad_inv6",
        "parent": "load_80",
        "flags": "DELTAMODE",
        "rated_power": "100 kW",
        "control_mode": "GRID_FORMING",
        "Pref": "70000",
        "Qref": "0.0",
        "Rfilter": "0.0025",
        "Xfilter": "0.05",
        "mp": "3.77",
        "kppmax": "10",
        "kipmax": "20",
        "Pmax": "1.2",
        "Pmin": "0",
        "mq": "0.05"
      },
      "children": []
    }
  ],
  "modules": [],
  "directives": [],
  "definitions": [],
  "schedules": []
}
